databaseconnectionmongo/__init__.py
databaseconnectionmongo/mongo_crud.py
databaseconnectionmongo-0.0.10.dist-info/LICENSE
databaseconnectionmongo-0.0.10.dist-info/METADATA
databaseconnectionmongo-0.0.10.dist-info/WHEEL
databaseconnectionmongo-0.0.10.dist-info/top_level.txt
databaseconnectionmongo-0.0.10.dist-info/RECORD
